blueautomata/__init__.py
blueautomata/automation_report.py
blueautomata/batch_export.py
blueautomata/data_compilation.py
blueautomata/inconsistency.py
blueautomata/system_cube.py
blueautomata/to_vba.py
blueautomata-1.0.dist-info/LICENSE.txt
blueautomata-1.0.dist-info/METADATA
blueautomata-1.0.dist-info/WHEEL
blueautomata-1.0.dist-info/top_level.txt
blueautomata-1.0.dist-info/RECORD
